hboard_widget/__init__.py
hboard_widget/_version.py
hboard_widget/callbacks.py
hboard_widget/widget.py
hboard_widget/labextension/package.json
hboard_widget/labextension/static/261.e1c74786b1430d7345d5.js
hboard_widget/labextension/static/486.09078e95b743cc5fab96.js
hboard_widget/labextension/static/486.09078e95b743cc5fab96.js.LICENSE.txt
hboard_widget/labextension/static/568.098d903bb5e0adcef496.js
hboard_widget/labextension/static/645.f7dd4f2c2bcfe98bf149.js
hboard_widget/labextension/static/645.f7dd4f2c2bcfe98bf149.js.LICENSE.txt
hboard_widget/labextension/static/remoteEntry.78de822e7ce2f15d5f5c.js
hboard_widget/labextension/static/style.js
hboard_widget/labextension/static/third-party-licenses.json
hboard_widget/nbextension/extension.js
hboard_widget/nbextension/index.js
hboard_widget/nbextension/index.js.LICENSE.txt
hboard_widget/tests/__init__.py
hboard_widget-0.1.1.data/data/etc/jupyter/nbconfig/notebook.d/hboard_widget.json
hboard_widget-0.1.1.data/data/share/jupyter/labextensions/hboard_widget/install.json
hboard_widget-0.1.1.data/data/share/jupyter/labextensions/hboard_widget/package.json
hboard_widget-0.1.1.data/data/share/jupyter/labextensions/hboard_widget/static/261.e1c74786b1430d7345d5.js
hboard_widget-0.1.1.data/data/share/jupyter/labextensions/hboard_widget/static/486.09078e95b743cc5fab96.js
hboard_widget-0.1.1.data/data/share/jupyter/labextensions/hboard_widget/static/486.09078e95b743cc5fab96.js.LICENSE.txt
hboard_widget-0.1.1.data/data/share/jupyter/labextensions/hboard_widget/static/568.098d903bb5e0adcef496.js
hboard_widget-0.1.1.data/data/share/jupyter/labextensions/hboard_widget/static/645.f7dd4f2c2bcfe98bf149.js
hboard_widget-0.1.1.data/data/share/jupyter/labextensions/hboard_widget/static/645.f7dd4f2c2bcfe98bf149.js.LICENSE.txt
hboard_widget-0.1.1.data/data/share/jupyter/labextensions/hboard_widget/static/remoteEntry.78de822e7ce2f15d5f5c.js
hboard_widget-0.1.1.data/data/share/jupyter/labextensions/hboard_widget/static/style.js
hboard_widget-0.1.1.dist-info/METADATA
hboard_widget-0.1.1.dist-info/WHEEL
hboard_widget-0.1.1.dist-info/top_level.txt
hboard_widget-0.1.1.dist-info/RECORD
