Metadata-Version: 2.1
Name: hboard-widget
Version: 0.1.1
Summary: Jupyter widgets for hypernets
Home-page: https://github.com/DataCanvasIO/HyperBoard.git
Author: wuhf
Author-email: wuhf@zetyun.com
Keywords: hypernets,jupyter,widgets
Classifier: Development Status :: 4 - Beta
Classifier: Framework :: IPython
Classifier: Intended Audience :: Developers
Classifier: Intended Audience :: Science/Research
Classifier: Topic :: Multimedia :: Graphics
Classifier: Programming Language :: Python :: 3.6
Classifier: Programming Language :: Python :: 3.7
Classifier: Programming Language :: Python :: 3.8
Classifier: Programming Language :: Python :: 3.9
Requires-Dist: ipywidgets (<9,>=7)
Requires-Dist: hypernets (<0.2.6,>=0.2.5.1)
